{
  "kind": "collectionType",
  "collectionName": "jobs",
  "info": {
    "name": "Jobs",
    "description": ""
  },
  "options": {
    "increments": true,
    "timestamps": true,
    "draftAndPublish": true
  },
  "pluginOptions": {},
  "attributes": {
    "title": {
      "type": "string",
      "required": true
    },
    "description": {
      "type": "richtext"
    },
    "applicationUrl": {
      "type": "string",
      "required": true
    },
    "companyName": {
      "type": "string",
      "required": true
    },
    "companyUrl": {
      "type": "string"
    }
  }
}
